isend/__init__.py
isend/client.py
isend_python_api-0.1.1.dist-info/licenses/LICENSE
isend_python_api-0.1.1.dist-info/METADATA
isend_python_api-0.1.1.dist-info/WHEEL
isend_python_api-0.1.1.dist-info/top_level.txt
isend_python_api-0.1.1.dist-info/RECORD
