Metadata-Version: 2.4
Name: isend-python-api
Version: 0.1.1
Summary: Python SDK for iSend API
Home-page: https://github.com/devmanoharrr/isend-python-api
Author: Manohar Reddy
Author-email: devmanoharrr@gmail.com
Classifier: Programming Language :: Python :: 3
Classifier: License :: OSI Approved :: MIT License
Requires-Python: >=3.6
License-File: LICENSE
Requires-Dist: requests
Dynamic: author
Dynamic: author-email
Dynamic: classifier
Dynamic: description
Dynamic: description-content-type
Dynamic: home-page
Dynamic: license-file
Dynamic: requires-dist
Dynamic: requires-python
Dynamic: summary
